tests/__init__.py
wexample_wex_addon_default/__init__.py
wexample_wex_addon_default/const/__init__.py
wexample_wex_addon_default/const/types.py
wexample_wex_addon_default/helpers/__init__.py
wexample_wex_addon_default/helpers/version.py
wexample_wex_addon_default/instructions/__init__.py
wexample_wex_addon_default/instructions/version/__init__.py
wexample_wex_addon_default/instructions/version/increment.py
wexample_wex_addon_default/tests/__init__.py
wexample_wex_addon_default/wexample_wexample_wex_addon_default/__init__.py
wexample_wex_addon_default-0.0.11.dist-info/.wex/.env
wexample_wex_addon_default-0.0.11.dist-info/.wex/config.yml
wexample_wex_addon_default-0.0.11.dist-info/.gitignore
wexample_wex_addon_default-0.0.11.dist-info/METADATA
wexample_wex_addon_default-0.0.11.dist-info/README.md
wexample_wex_addon_default-0.0.11.dist-info/WHEEL
wexample_wex_addon_default-0.0.11.dist-info/__init__.py
wexample_wex_addon_default-0.0.11.dist-info/setup.py
wexample_wex_addon_default-0.0.11.dist-info/top_level.txt
wexample_wex_addon_default-0.0.11.dist-info/version.txt
wexample_wex_addon_default-0.0.11.dist-info/RECORD
