Metadata-Version: 2.1
Name: wexample-wex-addon-default
Version: 0.0.11
Summary: Some python basic helpers and constants.
Home-page: https://github.com/wexample/python-helpers
Author: weeger
Author-email: contact@wexample.com
Classifier: Programming Language :: Python :: 3
Classifier: License :: OSI Approved :: MIT License
Classifier: Operating System :: OS Independent
Requires-Python: >=3.6
